mkdocs_substitute_plugin/__init__.py
mkdocs_substitute_plugin-0.0.13.dist-info/METADATA
mkdocs_substitute_plugin-0.0.13.dist-info/WHEEL
mkdocs_substitute_plugin-0.0.13.dist-info/entry_points.txt
mkdocs_substitute_plugin-0.0.13.dist-info/top_level.txt
mkdocs_substitute_plugin-0.0.13.dist-info/RECORD
