Metadata-Version: 2.4
Name: mkdocs_substitute_plugin
Version: 0.0.13
Summary: Package for Text/Element Replacements in mkdocs used with the Material Theme
Author-email: Peter Killert <mkdocs@code-is-poetry.de>
License-Expression: MIT
Project-URL: Homepage, https://www.code-is-poetry.de/substitute/
Project-URL: Issues, https://www.code-is-poetry.de/substitute/
Classifier: Programming Language :: Python :: 3
Classifier: Operating System :: OS Independent
Requires-Python: >=3.9
Requires-Dist: feedparser>=6.0
Requires-Dist: mkdocs>=1.5
Requires-Dist: mkdocs-material>=9.0
